urltk/__init__.py
urltk-1.0.1.dist-info/WHEEL
urltk-1.0.1.dist-info/METADATA
urltk-1.0.1.dist-info/RECORD
